joeypan/__init__.py
joeypan/config/__init__.py
joeypan/config/settings.py
joeypan/resource/template.json
joeypan/test/__init__.py
joeypan/test/models.py
joeypan/test/test_export_model.py
joeypan/test/test_settings.py
joeypan/utils/ErrorCode.py
joeypan/utils/__init__.py
joeypan/utils/exceptions.py
joeypan-0.0.8.data/data/template/template.json
joeypan-0.0.8.dist-info/LICENSE
joeypan-0.0.8.dist-info/METADATA
joeypan-0.0.8.dist-info/WHEEL
joeypan-0.0.8.dist-info/top_level.txt
joeypan-0.0.8.dist-info/RECORD
