Metadata-Version: 2.1
Name: joeypan
Version: 0.0.8
Summary: A small package for web framework
Home-page: http://www.joeypan.cn:9830/Elijahxb/joeypan
Author: elijahxb
Author-email: elijahxb@outlook.com
Classifier: Programming Language :: Python :: 3
Classifier: License :: OSI Approved :: MIT License
Classifier: Operating System :: OS Independent
License-File: LICENSE
Requires-Dist: pydantic (==1.10.6)
Requires-Dist: sqlalchemy (==2.0.6)
Requires-Dist: pymysql (==1.0.3)
Requires-Dist: elasticsearch (==7.8.0)
Requires-Dist: redis (==4.5.4)
